sql_metadata_lineage/__init__.py
sql_metadata_lineage-0.0.1.dist-info/LICENSE
sql_metadata_lineage-0.0.1.dist-info/METADATA
sql_metadata_lineage-0.0.1.dist-info/WHEEL
sql_metadata_lineage-0.0.1.dist-info/top_level.txt
sql_metadata_lineage-0.0.1.dist-info/RECORD
