Metadata-Version: 2.1
Name: sql-metadata-lineage
Version: 0.0.1
Summary: Package to get SQL query metadata(first level lineage), column -> database.table.actual_column mapping along with table alias mapping(alias -> database.table)
Home-page: https://github.com/PraveenKumar-21/sql_metadata_lineage
Author: Praveen Kumar B
Author-email: bpraveenkumar21@gmail.com
License: UNKNOWN
Keywords: SQL metadata,SQL parse metadata,Metadata lineage for SQL,SQL Lineage
Platform: UNKNOWN
Classifier: Programming Language :: Python :: 3
Classifier: License :: OSI Approved :: MIT License
Classifier: Operating System :: OS Independent
Requires-Python: >=3.6
Requires-Dist: sqlparse
